imio.zamqp.core-0.11-py3.12-nspkg.pth
imio/zamqp/core/__init__.py
imio/zamqp/core/base.py
imio/zamqp/core/configure.zcml
imio/zamqp/core/consumer.py
imio/zamqp/core/interfaces.py
imio/zamqp/core/producer.py
imio/zamqp/core/testing.py
imio/zamqp/core/testing.zcml
imio/zamqp/core/utils.py
imio/zamqp/core/profiles/testing/metadata.xml
imio/zamqp/core/profiles/testing/types.xml
imio/zamqp/core/profiles/testing/types/testingtype.xml
imio/zamqp/core/tests/__init__.py
imio/zamqp/core/tests/test_utils.py
imio_zamqp_core-0.11.dist-info/METADATA
imio_zamqp_core-0.11.dist-info/WHEEL
imio_zamqp_core-0.11.dist-info/namespace_packages.txt
imio_zamqp_core-0.11.dist-info/top_level.txt
imio_zamqp_core-0.11.dist-info/RECORD
