Metadata-Version: 2.4
Name: imio.zamqp.core
Version: 0.11
Summary: Generic methods tu use amqp
Home-page: https://github.com/imio/
Author: IMIO
Author-email: support@imio.be
License: GPL
Keywords: Plone Python IMIO
Classifier: Environment :: Web Environment
Classifier: Framework :: Plone
Classifier: Operating System :: OS Independent
Classifier: Programming Language :: Python
Classifier: Programming Language :: Python :: 2.7
Classifier: Topic :: Software Development :: Libraries :: Python Modules
Requires-Dist: setuptools
Requires-Dist: collective.zamqp
Requires-Dist: imio.dataexchange.core
Requires-Dist: imio.helpers
Requires-Dist: plone.dexterity
Requires-Dist: requests
Provides-Extra: test
Requires-Dist: plone.app.testing; extra == "test"
Requires-Dist: collective.dms.scanbehavior>1.3.1; extra == "test"
Requires-Dist: plone.app.dexterity; extra == "test"
Dynamic: author
Dynamic: author-email
Dynamic: classifier
Dynamic: description
Dynamic: home-page
Dynamic: keywords
Dynamic: license
Dynamic: provides-extra
Dynamic: requires-dist
Dynamic: summary
